IPNBvideoembed/__init__.py
IPNBvideoembed/custom_exception.py
IPNBvideoembed/logger.py
IPNBvideoembed/site.py
IPNBvideoembed/youtube.py
IPNB_video_embed-0.0.3.dist-info/LICENSE
IPNB_video_embed-0.0.3.dist-info/METADATA
IPNB_video_embed-0.0.3.dist-info/WHEEL
IPNB_video_embed-0.0.3.dist-info/top_level.txt
IPNB_video_embed-0.0.3.dist-info/RECORD
